AUTHORS.txt
CHANGES.txt
MANIFEST.in
README.md
setup.py
appconfig/__init__.py
appconfig/appconfig.py
appconfig.egg-info/PKG-INFO
appconfig.egg-info/SOURCES.txt
appconfig.egg-info/dependency_links.txt
appconfig.egg-info/requires.txt
appconfig.egg-info/top_level.txt
tests/__init__.py
tests/appconfig_tests.py